.gitignore
LICENSE
MANIFEST.in
README.md
pyproject.toml
setup.py
.github/workflows/build_python_package.yml
examples/compile_with_tasks.py
examples/denolser.py
examples/dynamic_geometry.py
examples/dynamic_materials.py
examples/hello.py
examples/spheres.py
examples/triangle.py
examples/cuda/dynamic_geometry.cu
examples/cuda/dynamic_geometry.h
examples/cuda/dynamic_geometry_vertex_generation.cu
examples/cuda/dynamic_materials.cu
examples/cuda/dynamic_materials.h
examples/cuda/hello.cu
examples/cuda/hello.h
examples/cuda/helpers.h
examples/cuda/sphere.h
examples/cuda/spheres.cu
examples/cuda/triangle.cu
examples/cuda/triangle.h
examples/cuda/vec_math.h
examples/sutil/__init__.py
examples/sutil/camera.py
examples/sutil/cuda_output_buffer.py
examples/sutil/gl_display.py
examples/sutil/gui.py
examples/sutil/properties.py
examples/sutil/trackball.py
examples/sutil/vecmath.py
optix/__init__.pxd
optix/__init__.py
optix/_version.py
optix/base.pxd
optix/base.pyx
optix/build.pxd
optix/build.pyx
optix/common.pxd
optix/common.py
optix/context.pxd
optix/context.pyx
optix/denoiser.pxd
optix/denoiser.pyx
optix/logging_utility.py
optix/micromap.pxd
optix/micromap.pyx
optix/module.pxd
optix/module.pyx
optix/optix_includes.h
optix/path_utility.py
optix/pipeline.pxd
optix/pipeline.pyx
optix/program_group.pxd
optix/program_group.pyx
optix/shader_binding_table.pxd
optix/shader_binding_table.pyx
optix/struct.pxd
optix/struct.pyx
python_optix.egg-info/PKG-INFO
python_optix.egg-info/SOURCES.txt
python_optix.egg-info/dependency_links.txt
python_optix.egg-info/not-zip-safe
python_optix.egg-info/requires.txt
python_optix.egg-info/top_level.txt