Metadata-Version: 2.1
Name: python-optix
Version: 1.0.0
Summary: Python bindings to the OptiX raytracing engine by nvidia
Home-page: https://github.com/mortacious/python-optix
Author: Felix Igelbrink
Author-email: felix.igelbrink@uni-osnabrueck.de
License: MIT
Project-URL: Bug Tracker, https://github.com/mortacious/python-optix/issues
Classifier: Programming Language :: Python :: 3.8
Classifier: Programming Language :: Python :: 3.9
Classifier: Programming Language :: Python :: 3.10
Classifier: License :: OSI Approved :: MIT License
Classifier: Operating System :: POSIX :: Linux
Classifier: Operating System :: Microsoft :: Windows
Classifier: Environment :: GPU :: NVIDIA CUDA
Classifier: Development Status :: 4 - Beta
Classifier: Intended Audience :: Science/Research
Classifier: Intended Audience :: Developers
Classifier: Topic :: Scientific/Engineering
Classifier: Topic :: Software Development
Requires-Python: >=3.8
Provides-Extra: examples
License-File: LICENSE
